radicalbit_platform_sdk/__init__.py
radicalbit_platform_sdk/apis/__init__.py
radicalbit_platform_sdk/apis/api_key.py
radicalbit_platform_sdk/apis/model.py
radicalbit_platform_sdk/apis/model_completion_dataset.py
radicalbit_platform_sdk/apis/model_current_dataset.py
radicalbit_platform_sdk/apis/model_reference_dataset.py
radicalbit_platform_sdk/apis/project.py
radicalbit_platform_sdk/apis/tracing_dashboard.py
radicalbit_platform_sdk/apis/tracing_root_trace.py
radicalbit_platform_sdk/apis/tracing_session.py
radicalbit_platform_sdk/charts/__init__.py
radicalbit_platform_sdk/charts/binary_classification/__init__.py
radicalbit_platform_sdk/charts/binary_classification/binary_chart.py
radicalbit_platform_sdk/charts/binary_classification/binary_chart_data.py
radicalbit_platform_sdk/charts/common/__init__.py
radicalbit_platform_sdk/charts/common/chart.py
radicalbit_platform_sdk/charts/common/chart_data.py
radicalbit_platform_sdk/charts/common/utils.py
radicalbit_platform_sdk/charts/multi_classification/__init__.py
radicalbit_platform_sdk/charts/multi_classification/multi_class_chart.py
radicalbit_platform_sdk/charts/multi_classification/multi_class_chart_data.py
radicalbit_platform_sdk/charts/radicalbit_sdk_chart.py
radicalbit_platform_sdk/charts/radicalbit_sdk_chart_data.py
radicalbit_platform_sdk/charts/regression/__init__.py
radicalbit_platform_sdk/charts/regression/regression_chart.py
radicalbit_platform_sdk/charts/regression/regression_chart_data.py
radicalbit_platform_sdk/client.py
radicalbit_platform_sdk/commons/__init__.py
radicalbit_platform_sdk/commons/rest_utils.py
radicalbit_platform_sdk/errors/__init__.py
radicalbit_platform_sdk/errors/errors.py
radicalbit_platform_sdk/models/__init__.py
radicalbit_platform_sdk/models/api_key_definition.py
radicalbit_platform_sdk/models/aws_credentials.py
radicalbit_platform_sdk/models/column_definition.py
radicalbit_platform_sdk/models/completion_response.py
radicalbit_platform_sdk/models/data_type.py
radicalbit_platform_sdk-1.4.0.dist-info/METADATA
radicalbit_platform_sdk-1.4.0.dist-info/WHEEL
radicalbit_platform_sdk-1.4.0.dist-info/RECORD
