Metadata-Version: 2.1
Name: radicalbit-platform-sdk
Version: 1.4.0
Summary: 
Author: dev.team
Author-email: devs@radicalbit.io
Requires-Python: >=3.11,<4.0
Classifier: Programming Language :: Python :: 3
Classifier: Programming Language :: Python :: 3.11
Classifier: Programming Language :: Python :: 3.12
Provides-Extra: chart
Requires-Dist: boto3 (>=1.34.111,<2.0.0)
Requires-Dist: ipecharts (==1.0.8) ; extra == "chart"
Requires-Dist: pandas (>=2.2.2,<3.0.0)
Requires-Dist: pydantic (>=2.7.1,<3.0.0)
Requires-Dist: requests (>=2.31.0,<3.0.0)
